test_pub_pypi/__init__.py
test_pub_pypi-0.3.0.dist-info/METADATA
test_pub_pypi-0.3.0.dist-info/WHEEL
test_pub_pypi-0.3.0.dist-info/RECORD
