Metadata-Version: 2.1
Name: test-pub-pypi
Version: 0.3.0
Summary: Testing pypi
Author: Woven
Author-email: woven@wovencollab.com
Requires-Python: >=3.10,<4.0
Classifier: Programming Language :: Python :: 3
Classifier: Programming Language :: Python :: 3.10
Classifier: Programming Language :: Python :: 3.11
Classifier: Programming Language :: Python :: 3.12
Requires-Dist: requests (>=2.26.0,<3.0.0)
Project-URL: Documentation, https://google.com
Project-URL: HomePage, https://google.com
